niseq/__init__.py
niseq/_clustering.py
niseq/_permutation.py
niseq/cluster_test.py
niseq/max_test.py
niseq/spending_functions.py
niseq/power/__init__.py
niseq/power/bootstrap.py
niseq/power/tests/__init__.py
niseq/power/tests/test_bootstrap.py
niseq/tests/__init__.py
niseq/tests/test_cluster_tests.py
niseq/tests/test_permutation.py
niseq/util/__init__.py
niseq/util/docs.py
niseq/util/tests/__init__.py
niseq/util/tests/test_docs.py
niseq-0.0.2.post1.dist-info/LICENSE.md
niseq-0.0.2.post1.dist-info/METADATA
niseq-0.0.2.post1.dist-info/WHEEL
niseq-0.0.2.post1.dist-info/top_level.txt
niseq-0.0.2.post1.dist-info/RECORD
