Metadata-Version: 2.1
Name: niseq
Version: 0.0.2.post1
Summary: Group sequential tests for neuroimaging
Home-page: https://github.com/john-veillette/niseq
Author: John Veillette
Author-email: johnv@uchicago.edu
License: BSD-3-Clause
Classifier: Intended Audience :: Science/Research
Classifier: Intended Audience :: Developers
Classifier: License :: OSI Approved
Classifier: Programming Language :: Python
Classifier: Topic :: Software Development
Classifier: Topic :: Scientific/Engineering
Classifier: Operating System :: Microsoft :: Windows
Classifier: Operating System :: POSIX
Classifier: Operating System :: Unix
Classifier: Operating System :: MacOS
Classifier: Programming Language :: Python :: 3
License-File: LICENSE.md
Requires-Dist: mne (>=1.0)
